g6/__init__.py
g6/frontend/dist/index.html
g6/frontend/dist/assets/favicon.63a26457.svg
g6/frontend/dist/assets/index.7fdeb11a.js
g6/frontend/dist/assets/index.bac77702.js
g6/frontend/dist/assets/vendor.0a793b15.js
g6/frontend/dist/assets/vendor.6ca40707.js
streamlit_antv-0.0.2.dist-info/METADATA
streamlit_antv-0.0.2.dist-info/WHEEL
streamlit_antv-0.0.2.dist-info/top_level.txt
streamlit_antv-0.0.2.dist-info/RECORD
