Metadata-Version: 2.1
Name: streamlit-antv
Version: 0.0.2
Summary: Antv charts custom component for Streamlit
Home-page: https://github.com/ais-one/favv
Author: Aaron Gong
Author-email: aaronjxz@gmail.com
License: MIT License
Keywords: streamlit,antv,charts
Platform: UNKNOWN
Classifier: Development Status :: 2 - Pre-Alpha
Classifier: Intended Audience :: Developers
Classifier: License :: OSI Approved :: MIT License
Classifier: Programming Language :: Python :: 3
Requires-Python: >=3.6
Requires-Dist: streamlit (>=0.63)
